<annotation>
	<folder>images</folder>
	<filename>img_20180417181917610_2.jpg</filename>
	<path>/home/ubuntu/dataset/dataset/images/img_20180417181917610_2.jpg</path>
	<source>
		<database>Unknown</database>
	</source>
	<size>
		<width>540</width>
		<height>540</height>
		<depth>3</depth>
	</size>
	<segmented>0</segmented>
	<object>
		<name>D00</name>
		<pose>Unspecified</pose>
		<truncated>0</truncated>
		<difficult>0</difficult>
		<bndbox>
			<xmin>388</xmin>
			<ymin>112</ymin>
			<xmax>536</xmax>
			<ymax>225</ymax>
		</bndbox>
	</object>
	<object>
		<name>D20</name>
		<pose>Unspecified</pose>
		<truncated>1</truncated>
		<difficult>0</difficult>
		<bndbox>
			<xmin>40</xmin>
			<ymin>284</ymin>
			<xmax>534</xmax>
			<ymax>540</ymax>
		</bndbox>
	</object>
</annotation>
