<annotation>
	<folder>images</folder>
	<filename>morotuka00_20190419114102.jpg</filename>
	<path>/home/ubuntu/Desktop/RDDataset_2019-a/images/morotuka00_20190419114102.jpg</path>
	<source>
		<database>Unknown</database>
	</source>
	<size>
		<width>600</width>
		<height>600</height>
		<depth>3</depth>
	</size>
	<segmented>0</segmented>
	<object>
		<name>D20</name>
		<pose>Unspecified</pose>
		<truncated>0</truncated>
		<difficult>0</difficult>
		<bndbox>
			<xmin>228</xmin>
			<ymin>411</ymin>
			<xmax>343</xmax>
			<ymax>509</ymax>
		</bndbox>
	</object>
	<object>
		<name>D20</name>
		<pose>Unspecified</pose>
		<truncated>0</truncated>
		<difficult>0</difficult>
		<bndbox>
			<xmin>397</xmin>
			<ymin>409</ymin>
			<xmax>534</xmax>
			<ymax>534</ymax>
		</bndbox>
	</object>
</annotation>
